{
  "version": 2,
  "extractor": "papercropper",
  "tables": [
    {
      "url": "assets/tables/arxiv/2605.24266v1/table-001.webp",
      "caption": "",
      "page": 0,
      "index": 1,
      "width": 1245,
      "height": 467,
      "label": "Table"
    },
    {
      "url": "assets/tables/arxiv/2605.24266v1/table-002.webp",
      "caption": "",
      "page": 0,
      "index": 2,
      "width": 859,
      "height": 196,
      "label": "Table"
    },
    {
      "url": "assets/tables/arxiv/2605.24266v1/table-003.webp",
      "caption": "",
      "page": 0,
      "index": 3,
      "width": 605,
      "height": 359,
      "label": "Table"
    },
    {
      "url": "assets/tables/arxiv/2605.24266v1/table-004.webp",
      "caption": "",
      "page": 0,
      "index": 4,
      "width": 855,
      "height": 354,
      "label": "Table"
    },
    {
      "url": "assets/tables/arxiv/2605.24266v1/table-005.webp",
      "caption": "",
      "page": 0,
      "index": 5,
      "width": 1065,
      "height": 511,
      "label": "Table"
    }
  ]
}